engine_function_extension/__init__.py
engine_function_extension-1.0.5.dist-info/METADATA
engine_function_extension-1.0.5.dist-info/WHEEL
engine_function_extension-1.0.5.dist-info/top_level.txt
engine_function_extension-1.0.5.dist-info/RECORD
