Metadata-Version: 2.1
Name: engine-function-extension
Version: 1.0.5
Summary: Python Worker Extension
Home-page: https://github.com/jarvinia
Author: Jun Tu
Author-email: jun@openlearning.com
License: MIT
Platform: UNKNOWN
Classifier: Intended Audience :: End Users/Desktop
Classifier: Development Status :: 5 - Production/Stable
Classifier: Intended Audience :: End Users/Desktop
Classifier: License :: OSI Approved :: Apache Software License
Classifier: Programming Language :: Python
Classifier: Programming Language :: Python :: 3.7
Classifier: Programming Language :: Python :: 3.8
Classifier: Programming Language :: Python :: 3.9
Requires-Dist: azure-functions (<2.0.0,>=1.7.0)
Requires-Dist: python-hosts (==1.0.3)
